JsseCankaoZhinan/README.md
JsseCankaoZhinan/__init__.py
JsseCankaoZhinan/__main__.py
JsseCankaoZhinan/file.epub
JsseCankaoZhinan/index.html
JsseCankaoZhinan/css/__init__.py
JsseCankaoZhinan/css/annotations.css
JsseCankaoZhinan/css/main.css
JsseCankaoZhinan/css/normalize.css
JsseCankaoZhinan/css/popup.css
JsseCankaoZhinan/font/__init__.py
JsseCankaoZhinan/font/fontello.eot
JsseCankaoZhinan/font/fontello.svg
JsseCankaoZhinan/font/fontello.ttf
JsseCankaoZhinan/font/fontello.woff
JsseCankaoZhinan/img/__init__.py
JsseCankaoZhinan/img/annotator-glyph-sprite.png
JsseCankaoZhinan/img/annotator-icon-sprite.png
JsseCankaoZhinan/img/apple-touch-icon.png
JsseCankaoZhinan/img/cancelfullscreen.png
JsseCankaoZhinan/img/close.png
JsseCankaoZhinan/img/fullscreen.png
JsseCankaoZhinan/img/loader.gif
JsseCankaoZhinan/img/menu-icon.png
JsseCankaoZhinan/img/save.png
JsseCankaoZhinan/img/saved.png
JsseCankaoZhinan/img/settings-s.png
JsseCankaoZhinan/img/settings.png
JsseCankaoZhinan/img/star.png
JsseCankaoZhinan/js/__init__.py
JsseCankaoZhinan/js/epub.js
JsseCankaoZhinan/js/epub.min.js
JsseCankaoZhinan/js/epub.min.map
JsseCankaoZhinan/js/hooks.min.js
JsseCankaoZhinan/js/hooks.min.map
JsseCankaoZhinan/js/reader.js
JsseCankaoZhinan/js/reader.js.map
JsseCankaoZhinan/js/reader.min.js
JsseCankaoZhinan/js/reader.min.map
JsseCankaoZhinan/js/hooks/__init__.py
JsseCankaoZhinan/js/hooks/extensions/__init__.py
JsseCankaoZhinan/js/hooks/extensions/highlight.js
JsseCankaoZhinan/js/libs/__init__.py
JsseCankaoZhinan/js/libs/jquery.min.js
JsseCankaoZhinan/js/libs/localforage.min.js
JsseCankaoZhinan/js/libs/screenfull.js
JsseCankaoZhinan/js/libs/screenfull.min.js
JsseCankaoZhinan/js/libs/zip.min.js
JsseCankaoZhinan/js/plugins/__init__.py
JsseCankaoZhinan/js/plugins/hypothesis.js
JsseCankaoZhinan/js/plugins/search.js
jsse_cankao_zhinan-2024.3.1.0.dist-info/METADATA
jsse_cankao_zhinan-2024.3.1.0.dist-info/WHEEL
jsse_cankao_zhinan-2024.3.1.0.dist-info/entry_points.txt
jsse_cankao_zhinan-2024.3.1.0.dist-info/top_level.txt
jsse_cankao_zhinan-2024.3.1.0.dist-info/RECORD
